<DOMSymbolItem xmlns:xsi="http://www.w3.org/2001/XMLSchema-instance" xmlns="http://ns.adobe.com/xfl/2008/" name="grass 1" itemID="6615eca2-000001f6" symbolType="graphic" lastModified="1712712866">
  <timeline>
    <DOMTimeline name="grass 1" layerDepthEnabled="true">
      <layers>
        <DOMLayer name="Capa_1" color="#4FFF4F" current="true" isSelected="true">
          <frames>
            <DOMFrame index="0" keyMode="9728">
              <elements>
                <DOMShape>
                  <fills>
                    <FillStyle index="1">
                      <SolidColor color="#666600"/>
                    </FillStyle>
                  </fills>
                  <edges>
                    <Edge fillStyle1="1" edges="!3045 960S2[3015 1161 2816 1600!2816 1600|391 1600!391 1600[383 1585 375 1570!375 1570[285 1414 238 1329!238 1329[58 1002 0 680!0 680|0 640!0 640[3 749 192 899!192 899[247 943 372 1037!372 1037[486 1126 560 1200!560 1200|600 1200!600
 1200[594 926 768 623!768 623[878 443 938 342!938 342[1048 159 1120 0!1120 0[1181 58 1296 413!1296 413[1417 788 1520 920!1520 920[1625 609 1789 388!1789 388[1991 116 2245 40!2245 40|2365 40!2365 40[2365 308 2405 747!2405 747[2445 1186
 2445 1240!2445 1240[2518 1191 2599 1169!2599 1169[2645 1156 2726 1143!2726 1143[2866 1113 2965 960!2965 960|3045 960"/>
                    <Edge cubics="!391 1600(;1198,1600 2096,1600 2816,1600q391 1600 2816 1600);"/>
                    <Edge cubics="!0 680(;0,680 0,640 0,640q0 680 0 640);"/>
                    <Edge cubics="!0 640(;5,825 320,960 560,1200q0 640Q3 749q192 899Q247 943q372 1037Q486 1126q560 1200);"/>
                    <Edge cubics="!560 1200(;560,1200 600,1200 600,1200q560 1200 600 1200);"/>
                    <Edge cubics="!600 1200(;590,740 885,520 1120,0q600 1200Q594 926q768 623Q878 443q938 342Q1048 159q1120 0);"/>
                    <Edge cubics="!1120 0(;1250,125 1325,670 1520,920q1120 0Q1181 58q1296 413Q1417 788q1520 920);"/>
                    <Edge cubics="!1520 920(;1640,565 1875,150 2245,40q1520 920Q1625 609q1789 388Q1991 116q2245 40);"/>
                    <Edge cubics="!2245 40(;2245,40 2365,40 2365,40q2245 40 2365 40);"/>
                    <Edge cubics="!2365 40(2365,40;2365,505 2445,1060 2445,1240q2365 40Q2365 308q2405 747Q2445 1186q2445 1240);"/>
                    <Edge cubics="!2445 1240(2445,1240;2675,1085 2790,1230 2965,960q2445 1240Q2518 1191q2599 1169Q2645 1156q2726 1143Q2866 1113q2965 960);"/>
                    <Edge cubics="!2965 960(;2965,960 3005,960 3045,960q2965 960 3045 960);"/>
                    <Edge cubics="!3045 960(3045,960;3019,1128 2921,1368 2816,1600q3045 960Q3015 1161q2816 1600);"/>
                    <Edge cubics="!375 1570(;315,1466 269,1386 238,1329q375 1570Q285 1414q238 1329);"/>
                    <Edge cubics="!391 1600(;386,1590 380,1580 375,1570q391 1600Q383 1585q375 1570);"/>
                    <Edge cubics="!238 1329(238,1329;118,1111 39,895 0,680q238 1329Q58 1002q0 680);"/>
                  </edges>
                </DOMShape>
              </elements>
            </DOMFrame>
          </frames>
        </DOMLayer>
      </layers>
    </DOMTimeline>
  </timeline>
</DOMSymbolItem>